bridgeaihub/__init__.py
bridgeaihub/gpt.py
bridgeaihub/main.py
bridgeaihub-0.0.4.dist-info/LICENSE.txt
bridgeaihub-0.0.4.dist-info/METADATA
bridgeaihub-0.0.4.dist-info/WHEEL
bridgeaihub-0.0.4.dist-info/top_level.txt
bridgeaihub-0.0.4.dist-info/RECORD
