Metadata-Version: 2.1
Name: bridgeaihub
Version: 0.0.4
Home-page: https://github.com/bridgeaihub/AIModel_GPT2_TextGeneration
Author: bridgeaihub
Author-email: contactus@bridgeaihub.com
License: MIT
Keywords: bridge gpt
License-File: LICENSE.txt
Requires-Dist: streamlit
Requires-Dist: tensorflow
Requires-Dist: transformers
